{
    "status": {
        "timestamp": "2018-08-14T09:52:31.324Z",
        "error_code": 0,
        "error_message": null,
        "elapsed": 3,
        "credit_count": 1
    },
    "data": {
        "active_cryptocurrencies": 1833,
        "active_market_pairs": 13019,
        "active_exchanges": 213,
        "eth_dominance": 13.9668,
        "btc_dominance": 53.905,
        "quote": {
            "USD": {
                "total_market_cap": 193858064395.279,
                "total_volume_24h": 15393759728.6776,
                "last_updated": "2018-08-14T09:42:00.000Z"
            }
        },
        "last_updated": "2018-08-14T09:42:00.000Z"
    }
}
